decoder38/decoder38.v
module decoder38(a,b,c,out);
    input a;
    input b;
    input c;
    output reg [7:0] out;
    always @(*) begin
        case({a,b,c})
        3'b000:out=8'b0000_0001;
        3'b001:out=8'b0000_0010;
        3'b010:out=8'b0000_0100;
        3'b011:out=8'b0000_1000;
        3'b100:out=8'b0001_0000;
        3'b101:out=8'b0010_0000;
        3'b110:out=8'b0100_0000;
        3'b111:out=8'b1000_0000;
        endcase
    end
endmodule

decoder38/decoder38_tb.v
`timescale 1ns/1ns

module decoder38_tb();
    reg a,b,c;
    wire [7:0] out;
    initial begin
        $dumpfile("wave.vcd"); 
	    $dumpvars(0, decoder38_tb); 
        a=0;b=0;c=0;
        #100;
        a=0;b=0;c=1;
        #100;
        a=0;b=1;c=0;
        #100;
        a=0;b=1;c=1;
        #100;
        a=1;b=0;c=0;
        #100;
        a=1;b=0;c=1;
        #100;
        a=1;b=1;c=0;
        #100;
        a=1;b=1;c=1;
        #100;
        $finish;
    end
    decoder38 decoder38_1(a,b,c,out);
endmodule

decoder38/wave.vcd
$date
	Sun Oct 29 23:16:27 2023
$end
$version
	Icarus Verilog
$end
$timescale
	1ns
$end
$scope module decoder38_tb $end
$var wire 8 ! out [7:0] $end
$var reg 1 " a $end
$var reg 1 # b $end
$var reg 1 $ c $end
$scope module decoder38_1 $end
$var wire 1 " a $end
$var wire 1 # b $end
$var wire 1 $ c $end
$var reg 8 % out [7:0] $end
$upscope $end
$upscope $end
$enddefinitions $end
$comment Show the parameter values. $end
$dumpall
$end
#0
$dumpvars
b1 %
0$
0#
0"
b1 !
$end
#100
b10 !
b10 %
1$
#200
b100 !
b100 %
0$
1#
#300
b1000 !
b1000 %
1$
#400
b10000 !
b10000 %
0$
0#
1"
#500
b100000 !
b100000 %
1$
#600
b1000000 !
b1000000 %
0$
1#
#700
b10000000 !
b10000000 %
1$
